wagtailnest/__init__.py
wagtailnest/apps.py
wagtailnest/config.py
wagtailnest/edit_handlers.py
wagtailnest/endpoints.py
wagtailnest/forms.py
wagtailnest/image_formats.py
wagtailnest/routes.py
wagtailnest/serializers.py
wagtailnest/skeleton_data.py
wagtailnest/utils.py
wagtailnest/views.py
wagtailnest/templates/wagtailadmin/pages/_preview_button_on_create.html
wagtailnest/templates/wagtailadmin/pages/_preview_button_on_edit.html
wagtailnest/templates/wagtailusers/users/create.html
wagtailnest/templates/wagtailusers/users/edit.html
wagtailnest-0.2.2.dist-info/METADATA
wagtailnest-0.2.2.dist-info/RECORD
wagtailnest-0.2.2.dist-info/WHEEL
wagtailnest-0.2.2.dist-info/top_level.txt
